korapp/__init__.py
korapp/html_template.py
korapp/kordir.py
korapp/kordoc.py
korapp/korgen.py
korapp/kornew.py
korapp/utils.py
korapp/water.css
korapp-0.1.5.dist-info/DESCRIPTION.rst
korapp-0.1.5.dist-info/METADATA
korapp-0.1.5.dist-info/RECORD
korapp-0.1.5.dist-info/WHEEL
korapp-0.1.5.dist-info/entry_points.txt
korapp-0.1.5.dist-info/metadata.json
korapp-0.1.5.dist-info/top_level.txt
