Metadata-Version: 2.0
Name: korapp
Version: 0.1.5
Summary: Python package to generate app from mind map
Home-page: https://github.com/korakotlee
Author: Korakot Leemakdej
Author-email: kleemakdej@gmail.com
License: MIT
Keywords: mind map,app generator
Platform: UNKNOWN
Classifier: Environment :: Console
Classifier: Intended Audience :: Developers
Classifier: License :: OSI Approved :: MIT License
Classifier: Operating System :: OS Independent
Classifier: Programming Language :: Python
Classifier: Programming Language :: Python :: 3
Classifier: Topic :: Software Development :: Libraries :: Python Modules
Requires-Dist: untangle
Requires-Dist: stringcase
Requires-Dist: xmltodict
Requires-Dist: pyyaml
Requires-Dist: Flask
Requires-Dist: markdown2
